[
    {
        "endpointId":"DailyActivitySummary",
        "ignoredKeys":["goals"],
        "url":"https://api.fitbit.com/1/user/%s/activities/date/%s.json",
        "urlParameters":["USER_ID", "DATE"],
        "tables":[
            {
                "tableKey":"activities",
                "columns":[
                    {
                        "columnId":"activityId",
                        "columnType":"INTEGER"
                    },
                    {
                        "columnId":"activityParentId",
                        "columnType":"INTEGER"
                    },
                    {
                        "columnId":"activityParentName",
                        "columnType":"STRING",
                        "maxLength":200
                    },
                    {
                        "columnId":"calories",
                        "columnType":"INTEGER"
                    },
                    {
                        "columnId":"description",
                        "columnType":"STRING",
                        "maxLength":200
                    },
                    {
                        "columnId":"distance",
                        "columnType":"DOUBLE"
                    },
                    {
                        "columnId":"duration",
                        "columnType":"INTEGER"
                    },
                    {
                        "columnId":"hasStartTime",
                        "columnType":"BOOLEAN"
                    },
                    {
                        "columnId":"isFavorite",
                        "columnType":"BOOLEAN"
                    },
                    {
                        "columnId":"lastModified",
                        "columnType":"DATE"
                    },
                    {
                        "columnId":"logId",
                        "columnType":"INTEGER"
                    },
                    {
                        "columnId":"name",
                        "columnType":"STRING",
                        "maxLength":200
                    },
                    {
                        "columnId":"startDate",
                        "columnType":"STRING",
                        "maxLength":10
                    },
                    {
                        "columnId":"startTime",
                        "columnType":"STRING",
                        "maxLength":5
                    },
                    {
                        "columnId":"steps",
                        "columnType":"INTEGER"
                    }
                ]
            },
            {
                "tableKey":"summary",
                "columns":[
                    {
                        "columnId":"activeScore",
                        "columnType":"INTEGER"
                    },
                    {
                        "columnId":"activityCalories",
                        "columnType":"INTEGER"
                    },
                    {
                        "columnId":"caloriesBMR",
                        "columnType":"INTEGER"
                    },
                    {
                        "columnId":"caloriesOut",
                        "columnType":"INTEGER"
                    },
                    {
                        "columnId":"distances",
                        "columnType":"LARGETEXT"
                    },
                    {
                        "columnId":"elevation",
                        "columnType":"DOUBLE"
                    },
                    {
                        "columnId":"fairlyActiveMinutes",
                        "columnType":"INTEGER"
                    },
                    {
                        "columnId":"floors",
                        "columnType":"INTEGER"
                    },
                    {
                        "columnId":"heartRateZones",
                        "columnType":"LARGETEXT"
                    },
                    {
                        "columnId":"lightlyActiveMinutes",
                        "columnType":"INTEGER"
                    },
                    {
                        "columnId":"marginalCalories",
                        "columnType":"INTEGER"
                    },
                    {
                        "columnId":"restingHeartRate",
                        "columnType":"INTEGER"
                    },
                    {
                        "columnId":"sedentaryMinutes",
                        "columnType":"INTEGER"
                    },
                    {
                        "columnId":"steps",
                        "columnType":"INTEGER"
                    },
                    {
                        "columnId":"veryActiveMinutes",
                        "columnType":"INTEGER"
                    }
                ]
            }
        ]
    },
    {
        "endpointId":"HeartRate",
        "url":"https://api.fitbit.com/1/user/%s/activities/heart/date/%s/1d/1sec.json",
        "urlParameters":["USER_ID", "DATE"],
        "tables":[
            {
                "tableKey":"activities-heart",
                "columns":[
                    {
                        "columnId":"dateTime",
                        "columnType":"STRING",
                        "maxLength":10
                    },
                    {
                        "columnId":"value",
                        "columnType":"LARGETEXT"
                    }
                ]
            },
            {
                "tableKey":"activities-heart-intraday",
                "columns":[
                    {
                        "columnId":"dataset",
                        "columnType":"FILEHANDLEID"
                    },
                    {
                        "columnId":"datasetInterval",
                        "columnType":"INTEGER"
                    },
                    {
                        "columnId":"datasetType",
                        "columnType":"STRING",
                        "maxLength":6
                    }
                ]
            }
        ]
    },
    {
        "endpointId":"Sleep",
        "url":"https://api.fitbit.com/1.2/user/%s/sleep/date/%s.json",
        "urlParameters":["USER_ID", "DATE"],
        "tables":[
            {
                "tableKey":"sleep",
                "columns":[
                    {
                        "columnId":"dateOfSleep",
                        "columnType":"STRING",
                        "maxLength":10
                    },
                    {
                        "columnId":"duration",
                        "columnType":"INTEGER"
                    },
                    {
                        "columnId":"efficiency",
                        "columnType":"INTEGER"
                    },
                    {
                        "columnId":"infoCode",
                        "columnType":"INTEGER"
                    },
                    {
                        "columnId":"isMainSleep",
                        "columnType":"BOOLEAN"
                    },
                    {
                        "columnId":"levels",
                        "columnType":"LARGETEXT"
                    },
                    {
                        "columnId":"logId",
                        "columnType":"INTEGER"
                    },
                    {
                        "columnId":"minutesAfterWakeup",
                        "columnType":"INTEGER"
                    },
                    {
                        "columnId":"minutesAsleep",
                        "columnType":"INTEGER"
                    },
                    {
                        "columnId":"minutesAwake",
                        "columnType":"INTEGER"
                    },
                    {
                        "columnId":"minutesToFallAsleep",
                        "columnType":"INTEGER"
                    },
                    {
                        "columnId":"startTime",
                        "columnType":"STRING",
                        "maxLength":23
                    },
                    {
                        "columnId":"endTime",
                        "columnType":"STRING",
                        "maxLength":23
                    },
                    {
                        "columnId":"timeInBed",
                        "columnType":"INTEGER"
                    },
                    {
                        "columnId":"type",
                        "columnType":"STRING",
                        "maxLength":7
                    }
                ]
            },
            {
                "tableKey":"summary",
                "columns":[
                    {
                        "columnId":"stages",
                        "columnType":"LARGETEXT"
                    },
                    {
                        "columnId":"totalMinutesAsleep",
                        "columnType":"INTEGER"
                    },
                    {
                        "columnId":"totalSleepRecords",
                        "columnType":"INTEGER"
                    },
                    {
                        "columnId":"totalTimeInBed",
                        "columnType":"INTEGER"
                    }
                ]
            }
        ]
    }
]
